pyfasty/__init__.py
pyfasty/_pyfasty.cp312-win_amd64.pyd
pyfasty-0.1.0b2.dist-info/LICENCE.txt
pyfasty-0.1.0b2.dist-info/METADATA
pyfasty-0.1.0b2.dist-info/WHEEL
pyfasty-0.1.0b2.dist-info/top_level.txt
pyfasty-0.1.0b2.dist-info/RECORD
