Metadata-Version: 2.1
Name: pyfasty
Version: 0.1.0b2
Summary: 🚀 Native C-powered Python utilities: magic registry, auto events, premium console - Code 10x faster!
Author: Hakan KARADAG
Maintainer: Hakan KARADAG
License: Apache License
Project-URL: Homepage, https://github.com/hakan-karadag/pyfasty
Project-URL: Documentation, https://github.com/hakan-karadag/pyfasty#readme
Project-URL: Repository, https://github.com/hakan-karadag/pyfasty
Project-URL: Source Code, https://github.com/hakan-karadag/pyfasty
Project-URL: Bug Tracker, https://github.com/hakan-karadag/pyfasty/issues
Project-URL: Changelog, https://github.com/hakan-karadag/pyfasty/releases
Keywords: python,c-extension,performance,registry,console,logging,events,threading,native,fast,utilities
Classifier: Development Status :: 4 - Beta
Classifier: Intended Audience :: Developers
Classifier: License :: OSI Approved :: Apache Software License
Classifier: Operating System :: OS Independent
Classifier: Programming Language :: C
Classifier: Programming Language :: Python :: 3
Classifier: Programming Language :: Python :: 3.8
Classifier: Programming Language :: Python :: 3.9
Classifier: Programming Language :: Python :: 3.10
Classifier: Programming Language :: Python :: 3.11
Classifier: Programming Language :: Python :: 3.12
Classifier: Topic :: Software Development :: Libraries :: Python Modules
Classifier: Topic :: Software Development :: Libraries
Classifier: Topic :: System :: Logging
Classifier: Topic :: Utilities
Classifier: Topic :: Internet :: WWW/HTTP :: Dynamic Content
Requires-Python: >=3.8
Provides-Extra: dev
Requires-Dist: pytest>=7.0.0; extra == "dev"
Requires-Dist: black>=22.0.0; extra == "dev"
Requires-Dist: flake8>=4.0.0; extra == "dev"
Requires-Dist: mypy>=0.950; extra == "dev"
Requires-Dist: isort>=5.10.0; extra == "dev"
Requires-Dist: pre-commit>=2.17.0; extra == "dev"
Provides-Extra: docs
Requires-Dist: sphinx>=4.5.0; extra == "docs"
Requires-Dist: sphinx-rtd-theme>=1.0.0; extra == "docs"
Requires-Dist: myst-parser>=0.17.0; extra == "docs"
Provides-Extra: test
Requires-Dist: pytest>=7.0.0; extra == "test"
Requires-Dist: pytest-cov>=3.0.0; extra == "test"
Requires-Dist: pytest-benchmark>=3.4.0; extra == "test"
